{
    "/js/app.js": "/js/app.js?id=9c5e30216df8bfcfa8eb",
    "/js/app.min.js": "/js/app.min.js?id=9c5e30216df8bfcfa8eb",
    "/css/libs.css": "/css/libs.css?id=f6e1c33fad703ad8979b",
    "/css/libs.min.css": "/css/libs.min.css?id=f6e1c33fad703ad8979b",
    "/js/libs.js": "/js/libs.js?id=21da4ea90e5bbfafe4b7",
    "/js/libs.min.js": "/js/libs.min.js?id=21da4ea90e5bbfafe4b7",
    "/js/app2.js": "/js/app2.js?id=bf1d455f150a43b54b08",
    "/js/app2.min.js": "/js/app2.min.js?id=bf1d455f150a43b54b08",
    "/js/web.js": "/js/web.js?id=e78e715a3c7e999f1b75"
}
